[
  {
    "map": "XP0_Caspian",
    "gameId": "18014398528603836",
    "gameExpansions": [
      524288,
      0,
      1048576,
      268435456,
      2097152,
      4194304,
      8388608,
      8589934592,
      17179869184
    ],
    "mapMode": "64",
    "ip": "108.61.227.225",
    "matchId": "0",
    "protocolVersionString": "4900",
    "extendedInfo": {
      "message": "",
      "bannerUrl": "",
      "desc": ""
    },
    "game": 2048,
    "ranked": 1,
    "online": 1,
    "platform": 1,
    "tickRateMax": 30,
    "updatedAt": 1637177229,
    "slots": {
      "8": {
        "current": 0,
        "max": 0
      },
      "1": {
        "current": 0,
        "max": 20
      },
      "2": {
        "current": 1,
        "max": 62
      },
      "4": {
        "current": 0,
        "max": 2
      }
    },
    "guid": "07e14aba-0213-481e-854d-aa5defa9a3b0",
    "port": 30000,
    "punkbuster": 1,
    "playlist": 0,
    "gameExpansion": "524288",
    "name": "Skyhawks Australia | AU | Community Server #1",
    "settings": {},
    "fairfight": 1,
    "region": 64,
    "mapVariant": 0,
    "ping": 999,
    "serverType": 2,
    "experience": 0,
    "tickRate": 30,
    "hasPassword": 0,
    "maps": {
      "maps": [],
      "currentMapRound": -1,
      "nextMapIndex": -1,
      "currentMapIndex": -1,
      "numberMapRounds": -1
    },
    "secret": "",
    "preset": 8,
    "pingSite": "syd",
    "country": "au"
  },
  {
    "map": "MP_Journey",
    "gameId": "36028797038099645",
    "gameExpansions": [
      0,
      524288,
      17179869184,
      4194304
    ],
    "mapMode": "64",
    "ip": "103.193.80.35",
    "matchId": "0",
    "protocolVersionString": "4900",
    "extendedInfo": {
      "message": "",
      "bannerUrl": "",
      "desc": ""
    },
    "game": 2048,
    "ranked": 1,
    "online": 1,
    "platform": 1,
    "tickRateMax": 30,
    "updatedAt": 1637177229,
    "slots": {
      "8": {
        "current": 0,
        "max": 2
      },
      "1": {
        "current": 0,
        "max": 20
      },
      "2": {
        "current": 1,
        "max": 64
      }
    },
    "guid": "f58c8346-1c9e-48b0-84f0-8d5d09d2b9da",
    "port": 25200,
    "punkbuster": 1,
    "playlist": 0,
    "gameExpansion": "0",
    "name": "! [BEER BOOBS BACON] 1 | NO JETS | Noob Friendly",
    "settings": {},
    "fairfight": 1,
    "region": 64,
    "mapVariant": 0,
    "ping": 999,
    "serverType": 2,
    "experience": 0,
    "tickRate": 60,
    "hasPassword": 0,
    "maps": {
      "maps": [],
      "currentMapRound": -1,
      "nextMapIndex": -1,
      "currentMapIndex": -1,
      "numberMapRounds": -1
    },
    "secret": "",
    "preset": 8,
    "pingSite": "syd",
    "country": "au"
  }
]
